TaguchiGridSearchConverter/TaguchiGridSearchConverter.py
TaguchiGridSearchConverter/__init__.py
taguchigridsearchconverter-0.2.6.dist-info/licenses/LICENSE
tests/__init__.py
tests/conftest.py
tests/test_integration.py
tests/test_taguchi_grid_search_converter.py
taguchigridsearchconverter-0.2.6.dist-info/METADATA
taguchigridsearchconverter-0.2.6.dist-info/WHEEL
taguchigridsearchconverter-0.2.6.dist-info/top_level.txt
taguchigridsearchconverter-0.2.6.dist-info/RECORD
