Metadata-Version: 2.4
Name: TaguchiGridSearchConverter
Version: 0.2.6
Summary: Optimize hyperparameter search using Taguchi array principles
Home-page: https://github.com/thiswillbeyourgithub/TaguchiGridSearchConverter.git
License: GPLv3
Keywords: taguchi,grid-search,hyperparameter-optimization,machine-learning,experiment-design,parameter-tuning
Classifier: Programming Language :: Python :: 3
Classifier: License :: OSI Approved :: GNU General Public License v3 (GPLv3)
Classifier: Operating System :: OS Independent
Requires-Python: >=3.11
License-File: LICENSE
Requires-Dist: numpy>=1.24.0
Requires-Dist: scikit-learn>=1.3.0
Dynamic: classifier
Dynamic: description
Dynamic: description-content-type
Dynamic: home-page
Dynamic: keywords
Dynamic: license
Dynamic: license-file
Dynamic: requires-dist
Dynamic: requires-python
Dynamic: summary
